alrocar_weather_service/__init__.py
alrocar_weather_service/server.py
alrocar_weather_service-0.2.2.dist-info/METADATA
alrocar_weather_service-0.2.2.dist-info/WHEEL
alrocar_weather_service-0.2.2.dist-info/entry_points.txt
alrocar_weather_service-0.2.2.dist-info/RECORD
