Metadata-Version: 2.3
Name: alrocar-weather-service
Version: 0.2.2
Summary: A MCP server project to integrate OpenWeather API in Claude
Requires-Python: >=3.10
Requires-Dist: httpx>=0.27.2
Requires-Dist: mcp>=1.0.0
Requires-Dist: python-dotenv>=1.0.1
